{
	"constellations": [
		{
			"abbr": "And",
			"lines": [
				{
					"hip1": 677,
					"hip2": 3092
				},
				{
					"hip1": 3092,
					"hip2": 5447
				},
				{
					"hip1": 9640,
					"hip2": 5447
				},
				{
					"hip1": 5447,
					"hip2": 4436
				},
				{
					"hip1": 4436,
					"hip2": 3881
				}
			]
		},
		{
			"abbr": "Ant",
			"lines": [
				{
					"hip1": 51172,
					"hip2": 48926
				}
			]
		},
		{
			"abbr": "Aps",
			"lines": [
				{
					"hip1": 72370,
					"hip2": 81065
				},
				{
					"hip1": 81065,
					"hip2": 81852
				}
			]
		},
		{
			"abbr": "Aql",
			"lines": [
				{
					"hip1": 98036,
					"hip2": 97649
				},
				{
					"hip1": 97649,
					"hip2": 97278
				},
				{
					"hip1": 97649,
					"hip2": 95501
				},
				{
					"hip1": 95501,
					"hip2": 97804
				},
				{
					"hip1": 99473,
					"hip2": 97804
				},
				{
					"hip1": 95501,
					"hip2": 93747
				},
				{
					"hip1": 93747,
					"hip2": 93244
				},
				{
					"hip1": 95501,
					"hip2": 93805
				}
			]
		},
		{
			"abbr": "Aqr",
			"lines": [
				{
					"hip1": 106278,
					"hip2": 109074
				},
				{
					"hip1": 109074,
					"hip2": 110395
				},
				{
					"hip1": 110395,
					"hip2": 110960
				},
				{
					"hip1": 110960,
					"hip2": 111497
				},
				{
					"hip1": 111497,
					"hip2": 112961
				},
				{
					"hip1": 112961,
					"hip2": 114855
				},
				{
					"hip1": 114855,
					"hip2": 115438
				},
				{
					"hip1": 109074,
					"hip2": 110003
				},
				{
					"hip1": 110003,
					"hip2": 109139
				},
				{
					"hip1": 110003,
					"hip2": 111123
				},
				{
					"hip1": 111123,
					"hip2": 112716
				},
				{
					"hip1": 112716,
					"hip2": 113136
				},
				{
					"hip1": 113136,
					"hip2": 114341
				},
				{
					"hip1": 102618,
					"hip2": 106278
				}
			]
		},
		{
			"abbr": "Ara",
			"lines": [
				{
					"hip1": 88714,
					"hip2": 85792
				},
				{
					"hip1": 85792,
					"hip2": 83081
				},
				{
					"hip1": 83081,
					"hip2": 82363
				},
				{
					"hip1": 82363,
					"hip2": 85727
				},
				{
					"hip1": 85727,
					"hip2": 85267
				},
				{
					"hip1": 85267,
					"hip2": 85258
				},
				{
					"hip1": 85258,
					"hip2": 88714
				}
			]
		},
		{
			"abbr": "Ari",
			"lines": [
				{
					"hip1": 13209,
					"hip2": 9884
				},
				{
					"hip1": 9884,
					"hip2": 8903
				},
				{
					"hip1": 8903,
					"hip2": 8832
				}
			]
		},
		{
			"abbr": "Aur",
			"lines": [
				{
					"hip1": 28380,
					"hip2": 28360
				},
				{
					"hip1": 28360,
					"hip2": 24608
				},
				{
					"hip1": 24608,
					"hip2": 23453
				},
				{
					"hip1": 23453,
					"hip2": 23015
				},
				{
					"hip1": 25428,
					"hip2": 23015
				},
				{
					"hip1": 25428,
					"hip2": 28380
				}
			]
		},
		{
			"abbr": "Boo",
			"lines": [
				{
					"hip1": 71795,
					"hip2": 69673
				},
				{
					"hip1": 69673,
					"hip2": 72105
				},
				{
					"hip1": 72105,
					"hip2": 74666
				},
				{
					"hip1": 74666,
					"hip2": 73555
				},
				{
					"hip1": 73555,
					"hip2": 71075
				},
				{
					"hip1": 71075,
					"hip2": 71053
				},
				{
					"hip1": 71053,
					"hip2": 69673
				},
				{
					"hip1": 69673,
					"hip2": 67927
				},
				{
					"hip1": 67927,
					"hip2": 67459
				}
			]
		},
		{
			"abbr": "Cae",
			"lines": [
				{
					"hip1": 21060,
					"hip2": 21770
				},
				{
					"hip1": 21770,
					"hip2": 21861
				}
			]
		},
		{
			"abbr": "Cam",
			"lines": [
				{
					"hip1": 16228,
					"hip2": 18505
				},
				{
					"hip1": 18505,
					"hip2": 22783
				},
				{
					"hip1": 16228,
					"hip2": 17959
				},
				{
					"hip1": 17959,
					"hip2": 22783
				},
				{
					"hip1": 17959,
					"hip2": 25110
				}
			]
		},
		{
			"abbr": "Cap",
			"lines": [
				{
					"hip1": 100064,
					"hip2": 100345
				},
				{
					"hip1": 100345,
					"hip2": 104139
				},
				{
					"hip1": 104139,
					"hip2": 105515
				},
				{
					"hip1": 105515,
					"hip2": 106985
				},
				{
					"hip1": 106985,
					"hip2": 107556
				},
				{
					"hip1": 105515,
					"hip2": 105881
				},
				{
					"hip1": 105881,
					"hip2": 104139
				},
				{
					"hip1": 100345,
					"hip2": 102485
				},
				{
					"hip1": 104139,
					"hip2": 102978
				}
			]
		},
		{
			"abbr": "Car",
			"lines": [
				{
					"hip1": 45238,
					"hip2": 50099
				},
				{
					"hip1": 50099,
					"hip2": 52419
				},
				{
					"hip1": 52419,
					"hip2": 52468
				},
				{
					"hip1": 52468,
					"hip2": 54463
				},
				{
					"hip1": 54463,
					"hip2": 53253
				},
				{
					"hip1": 53253,
					"hip2": 51232
				},
				{
					"hip1": 51232,
					"hip2": 50371
				},
				{
					"hip1": 50371,
					"hip2": 45556
				},
				{
					"hip1": 42568,
					"hip2": 41037
				},
				{
					"hip1": 41037,
					"hip2": 30438
				},
				{
					"hip1": 45080,
					"hip2": 45556
				},
				{
					"hip1": 45080,
					"hip2": 42568
				},
				{
					"hip1": 30438,
					"hip2": 31685
				},
				{
					"hip1": 41037,
					"hip2": 39429
				}
			]
		},
		{
			"abbr": "Cas",
			"lines": [
				{
					"hip1": 8886,
					"hip2": 6686
				},
				{
					"hip1": 6686,
					"hip2": 4427
				},
				{
					"hip1": 4427,
					"hip2": 3179
				},
				{
					"hip1": 3179,
					"hip2": 746
				}
			]
		},
		{
			"abbr": "Cen",
			"lines": [
				{
					"hip1": 71683,
					"hip2": 68702
				},
				{
					"hip1": 68702,
					"hip2": 66657
				},
				{
					"hip1": 66657,
					"hip2": 68002
				},
				{
					"hip1": 68002,
					"hip2": 68282
				},
				{
					"hip1": 68282,
					"hip2": 67472
				},
				{
					"hip1": 67472,
					"hip2": 67464
				},
				{
					"hip1": 67464,
					"hip2": 65936
				},
				{
					"hip1": 65936,
					"hip2": 65109
				},
				{
					"hip1": 67464,
					"hip2": 68933
				},
				{
					"hip1": 67472,
					"hip2": 71352
				},
				{
					"hip1": 71352,
					"hip2": 73334
				},
				{
					"hip1": 68002,
					"hip2": 61932
				},
				{
					"hip1": 61932,
					"hip2": 60823
				},
				{
					"hip1": 60823,
					"hip2": 59196
				},
				{
					"hip1": 59196,
					"hip2": 56480
				},
				{
					"hip1": 56480,
					"hip2": 56561
				}
			]
		},
		{
			"abbr": "Cep",
			"lines": [
				{
					"hip1": 109492,
					"hip2": 112724
				},
				{
					"hip1": 112724,
					"hip2": 106032
				},
				{
					"hip1": 106032,
					"hip2": 105199
				},
				{
					"hip1": 105199,
					"hip2": 109492
				},
				{
					"hip1": 112724,
					"hip2": 116727
				},
				{
					"hip1": 116727,
					"hip2": 106032
				}
			]
		},
		{
			"abbr": "Cet",
			"lines": [
				{
					"hip1": 10324,
					"hip2": 11484
				},
				{
					"hip1": 8102,
					"hip2": 3419
				},
				{
					"hip1": 3419,
					"hip2": 1562
				},
				{
					"hip1": 3419,
					"hip2": 5364
				},
				{
					"hip1": 5364,
					"hip2": 6537
				},
				{
					"hip1": 6537,
					"hip2": 8645
				},
				{
					"hip1": 8645,
					"hip2": 11345
				},
				{
					"hip1": 11345,
					"hip2": 12390
				},
				{
					"hip1": 12390,
					"hip2": 12770
				},
				{
					"hip1": 12770,
					"hip2": 11783
				},
				{
					"hip1": 11783,
					"hip2": 8102
				},
				{
					"hip1": 10826,
					"hip2": 12390
				},
				{
					"hip1": 10826,
					"hip2": 12387
				},
				{
					"hip1": 12387,
					"hip2": 12706
				},
				{
					"hip1": 12706,
					"hip2": 14135
				},
				{
					"hip1": 14135,
					"hip2": 13954
				},
				{
					"hip1": 13954,
					"hip2": 12828
				},
				{
					"hip1": 12828,
					"hip2": 11484
				},
				{
					"hip1": 11484,
					"hip2": 12093
				},
				{
					"hip1": 12093,
					"hip2": 12706
				}
			]
		},
		{
			"abbr": "Cha",
			"lines": [
				{
					"hip1": 40702,
					"hip2": 51839
				},
				{
					"hip1": 51839,
					"hip2": 60000
				}
			]
		},
		{
			"abbr": "Cir",
			"lines": [
				{
					"hip1": 71908,
					"hip2": 75323
				},
				{
					"hip1": 71908,
					"hip2": 74824
				}
			]
		},
		{
			"abbr": "CMa",
			"lines": [
				{
					"hip1": 33160,
					"hip2": 34045
				},
				{
					"hip1": 34045,
					"hip2": 33347
				},
				{
					"hip1": 33347,
					"hip2": 32349
				},
				{
					"hip1": 32349,
					"hip2": 33977
				},
				{
					"hip1": 33977,
					"hip2": 34444
				},
				{
					"hip1": 34444,
					"hip2": 35037
				},
				{
					"hip1": 35037,
					"hip2": 35904
				},
				{
					"hip1": 33579,
					"hip2": 33856
				},
				{
					"hip1": 33856,
					"hip2": 34444
				},
				{
					"hip1": 33856,
					"hip2": 33165
				},
				{
					"hip1": 33165,
					"hip2": 31592
				},
				{
					"hip1": 31592,
					"hip2": 31416
				},
				{
					"hip1": 31592,
					"hip2": 30324
				},
				{
					"hip1": 31592,
					"hip2": 32349
				},
				{
					"hip1": 33579,
					"hip2": 32759
				},
				{
					"hip1": 30122,
					"hip2": 33579
				},
				{
					"hip1": 33347,
					"hip2": 33160
				}
			]
		},
		{
			"abbr": "CMi",
			"lines": [
				{
					"hip1": 37279,
					"hip2": 36188
				}
			]
		},
		{
			"abbr": "Cnc",
			"lines": [
				{
					"hip1": 43103,
					"hip2": 42806
				},
				{
					"hip1": 42806,
					"hip2": 40843
				},
				{
					"hip1": 42806,
					"hip2": 42911
				},
				{
					"hip1": 42911,
					"hip2": 40526
				},
				{
					"hip1": 42911,
					"hip2": 44066
				}
			]
		},
		{
			"abbr": "Col",
			"lines": [
				{
					"hip1": 30277,
					"hip2": 29807
				},
				{
					"hip1": 29807,
					"hip2": 28199
				},
				{
					"hip1": 28199,
					"hip2": 27628
				},
				{
					"hip1": 27628,
					"hip2": 28328
				},
				{
					"hip1": 27628,
					"hip2": 26634
				},
				{
					"hip1": 26634,
					"hip2": 25859
				}
			]
		},
		{
			"abbr": "Com",
			"lines": [
				{
					"hip1": 64241,
					"hip2": 64394
				},
				{
					"hip1": 64394,
					"hip2": 60742
				}
			]
		},
		{
			"abbr": "CrA",
			"lines": [
				{
					"hip1": 91875,
					"hip2": 92989
				},
				{
					"hip1": 92989,
					"hip2": 93174
				},
				{
					"hip1": 93174,
					"hip2": 93825
				},
				{
					"hip1": 93825,
					"hip2": 94114
				},
				{
					"hip1": 94114,
					"hip2": 94160
				},
				{
					"hip1": 94160,
					"hip2": 94005
				},
				{
					"hip1": 94005,
					"hip2": 93542
				},
				{
					"hip1": 93542,
					"hip2": 92953
				},
				{
					"hip1": 91875,
					"hip2": 90887
				}
			]
		},
		{
			"abbr": "CrB",
			"lines": [
				{
					"hip1": 76127,
					"hip2": 75695
				},
				{
					"hip1": 75695,
					"hip2": 76267
				},
				{
					"hip1": 76267,
					"hip2": 76952
				},
				{
					"hip1": 76952,
					"hip2": 77512
				},
				{
					"hip1": 77512,
					"hip2": 78159
				},
				{
					"hip1": 78159,
					"hip2": 78493
				}
			]
		},
		{
			"abbr": "Crt",
			"lines": [
				{
					"hip1": 53740,
					"hip2": 54682
				},
				{
					"hip1": 54682,
					"hip2": 55705
				},
				{
					"hip1": 55705,
					"hip2": 55282
				},
				{
					"hip1": 55282,
					"hip2": 53740
				},
				{
					"hip1": 55282,
					"hip2": 55687
				},
				{
					"hip1": 55687,
					"hip2": 56633
				},
				{
					"hip1": 56633,
					"hip2": 58188
				},
				{
					"hip1": 58188,
					"hip2": 57283
				},
				{
					"hip1": 57283,
					"hip2": 55705
				}
			]
		},
		{
			"abbr": "Cru",
			"lines": [
				{
					"hip1": 61084,
					"hip2": 60718
				},
				{
					"hip1": 62434,
					"hip2": 59747
				}
			]
		},
		{
			"abbr": "Crv",
			"lines": [
				{
					"hip1": 61174,
					"hip2": 60965
				},
				{
					"hip1": 60965,
					"hip2": 59803
				},
				{
					"hip1": 59803,
					"hip2": 59316
				},
				{
					"hip1": 59316,
					"hip2": 59199
				},
				{
					"hip1": 59316,
					"hip2": 61359
				},
				{
					"hip1": 61359,
					"hip2": 60965
				}
			]
		},
		{
			"abbr": "CVn",
			"lines": [
				{
					"hip1": 61317,
					"hip2": 63125
				}
			]
		},
		{
			"abbr": "Cyg",
			"lines": [
				{
					"hip1": 94779,
					"hip2": 95853
				},
				{
					"hip1": 95853,
					"hip2": 97165
				},
				{
					"hip1": 97165,
					"hip2": 100453
				},
				{
					"hip1": 100453,
					"hip2": 102098
				},
				{
					"hip1": 100453,
					"hip2": 102488
				},
				{
					"hip1": 102488,
					"hip2": 104732
				},
				{
					"hip1": 104732,
					"hip2": 107310
				},
				{
					"hip1": 100453,
					"hip2": 98110
				},
				{
					"hip1": 98110,
					"hip2": 95947
				}
			]
		},
		{
			"abbr": "Del",
			"lines": [
				{
					"hip1": 101421,
					"hip2": 101769
				},
				{
					"hip1": 101769,
					"hip2": 101958
				},
				{
					"hip1": 101958,
					"hip2": 102532
				},
				{
					"hip1": 102532,
					"hip2": 102281
				},
				{
					"hip1": 102281,
					"hip2": 101769
				}
			]
		},
		{
			"abbr": "Dor",
			"lines": [
				{
					"hip1": 27100,
					"hip2": 27890
				},
				{
					"hip1": 27890,
					"hip2": 26069
				},
				{
					"hip1": 26069,
					"hip2": 27100
				},
				{
					"hip1": 26069,
					"hip2": 21281
				},
				{
					"hip1": 21281,
					"hip2": 19893
				}
			]
		},
		{
			"abbr": "Dra",
			"lines": [
				{
					"hip1": 87585,
					"hip2": 87833
				},
				{
					"hip1": 87833,
					"hip2": 85670
				},
				{
					"hip1": 85670,
					"hip2": 85829
				},
				{
					"hip1": 85829,
					"hip2": 87585
				},
				{
					"hip1": 87585,
					"hip2": 94376
				},
				{
					"hip1": 94376,
					"hip2": 97433
				},
				{
					"hip1": 97433,
					"hip2": 94648
				},
				{
					"hip1": 94648,
					"hip2": 89937
				},
				{
					"hip1": 89937,
					"hip2": 83895
				},
				{
					"hip1": 83895,
					"hip2": 80331
				},
				{
					"hip1": 80331,
					"hip2": 78527
				},
				{
					"hip1": 78527,
					"hip2": 75458
				},
				{
					"hip1": 75458,
					"hip2": 68756
				},
				{
					"hip1": 68756,
					"hip2": 61281
				},
				{
					"hip1": 61281,
					"hip2": 56211
				}
			]
		},
		{
			"abbr": "Equ",
			"lines": [
				{
					"hip1": 104521,
					"hip2": 104858
				},
				{
					"hip1": 104858,
					"hip2": 105570
				},
				{
					"hip1": 105570,
					"hip2": 104987
				},
				{
					"hip1": 104987,
					"hip2": 104521
				}
			]
		},
		{
			"abbr": "Eri",
			"lines": [
				{
					"hip1": 7588,
					"hip2": 9007
				},
				{
					"hip1": 9007,
					"hip2": 10602
				},
				{
					"hip1": 10602,
					"hip2": 11407
				},
				{
					"hip1": 11407,
					"hip2": 12413
				},
				{
					"hip1": 12413,
					"hip2": 12486
				},
				{
					"hip1": 12486,
					"hip2": 13847
				},
				{
					"hip1": 13847,
					"hip2": 15510
				},
				{
					"hip1": 15510,
					"hip2": 17797
				},
				{
					"hip1": 17797,
					"hip2": 17874
				},
				{
					"hip1": 17874,
					"hip2": 20042
				},
				{
					"hip1": 20042,
					"hip2": 20535
				},
				{
					"hip1": 20535,
					"hip2": 21393
				},
				{
					"hip1": 21393,
					"hip2": 17651
				},
				{
					"hip1": 17651,
					"hip2": 16611
				},
				{
					"hip1": 16611,
					"hip2": 15474
				},
				{
					"hip1": 15474,
					"hip2": 14146
				},
				{
					"hip1": 14146,
					"hip2": 12843
				},
				{
					"hip1": 12843,
					"hip2": 13701
				},
				{
					"hip1": 13701,
					"hip2": 15197
				},
				{
					"hip1": 15197,
					"hip2": 16537
				},
				{
					"hip1": 16537,
					"hip2": 17378
				},
				{
					"hip1": 17378,
					"hip2": 21444
				},
				{
					"hip1": 21444,
					"hip2": 22109
				},
				{
					"hip1": 22109,
					"hip2": 22701
				},
				{
					"hip1": 22701,
					"hip2": 23875
				},
				{
					"hip1": 23875,
					"hip2": 23972
				},
				{
					"hip1": 23972,
					"hip2": 21594
				}
			]
		},
		{
			"abbr": "For",
			"lines": [
				{
					"hip1": 13147,
					"hip2": 14879
				}
			]
		},
		{
			"abbr": "Gem",
			"lines": [
				{
					"hip1": 31681,
					"hip2": 34088
				},
				{
					"hip1": 34088,
					"hip2": 35550
				},
				{
					"hip1": 35550,
					"hip2": 35350
				},
				{
					"hip1": 35350,
					"hip2": 32362
				},
				{
					"hip1": 35550,
					"hip2": 36962
				},
				{
					"hip1": 36962,
					"hip2": 37740
				},
				{
					"hip1": 36962,
					"hip2": 37826
				},
				{
					"hip1": 36962,
					"hip2": 36046
				},
				{
					"hip1": 36046,
					"hip2": 34693
				},
				{
					"hip1": 34693,
					"hip2": 36850
				},
				{
					"hip1": 34693,
					"hip2": 33018
				},
				{
					"hip1": 34693,
					"hip2": 32246
				},
				{
					"hip1": 32246,
					"hip2": 30883
				},
				{
					"hip1": 32246,
					"hip2": 30343
				},
				{
					"hip1": 30343,
					"hip2": 29655
				},
				{
					"hip1": 29655,
					"hip2": 28734
				}
			]
		},
		{
			"abbr": "Gru",
			"lines": [
				{
					"hip1": 114131,
					"hip2": 110997
				},
				{
					"hip1": 110997,
					"hip2": 109268
				},
				{
					"hip1": 109268,
					"hip2": 112122
				},
				{
					"hip1": 112122,
					"hip2": 114421
				},
				{
					"hip1": 114421,
					"hip2": 114131
				},
				{
					"hip1": 112122,
					"hip2": 113638
				},
				{
					"hip1": 112122,
					"hip2": 112623
				},
				{
					"hip1": 109268,
					"hip2": 109111
				},
				{
					"hip1": 109111,
					"hip2": 108085
				}
			]
		},
		{
			"abbr": "Her",
			"lines": [
				{
					"hip1": 86414,
					"hip2": 87808
				},
				{
					"hip1": 87808,
					"hip2": 85112
				},
				{
					"hip1": 85112,
					"hip2": 84606
				},
				{
					"hip1": 84606,
					"hip2": 84380
				},
				{
					"hip1": 84380,
					"hip2": 81833
				},
				{
					"hip1": 81833,
					"hip2": 81126
				},
				{
					"hip1": 81126,
					"hip2": 79992
				},
				{
					"hip1": 79992,
					"hip2": 77760
				},
				{
					"hip1": 81833,
					"hip2": 81693
				},
				{
					"hip1": 81693,
					"hip2": 80816
				},
				{
					"hip1": 80816,
					"hip2": 80170
				},
				{
					"hip1": 81693,
					"hip2": 83207
				},
				{
					"hip1": 83207,
					"hip2": 85693
				},
				{
					"hip1": 85693,
					"hip2": 84379
				},
				{
					"hip1": 86974,
					"hip2": 87933
				},
				{
					"hip1": 87933,
					"hip2": 88794
				},
				{
					"hip1": 83207,
					"hip2": 84380
				},
				{
					"hip1": 86974,
					"hip2": 85693
				}
			]
		},
		{
			"abbr": "Hor",
			"lines": [
				{
					"hip1": 19747,
					"hip2": 12484
				},
				{
					"hip1": 12484,
					"hip2": 14240
				}
			]
		},
		{
			"abbr": "Hya",
			"lines": [
				{
					"hip1": 42799,
					"hip2": 42402
				},
				{
					"hip1": 42402,
					"hip2": 42313
				},
				{
					"hip1": 42313,
					"hip2": 43109
				},
				{
					"hip1": 43109,
					"hip2": 43234
				},
				{
					"hip1": 43234,
					"hip2": 42799
				},
				{
					"hip1": 43234,
					"hip2": 43813
				},
				{
					"hip1": 43813,
					"hip2": 45336
				},
				{
					"hip1": 45336,
					"hip2": 46776
				},
				{
					"hip1": 46776,
					"hip2": 46509
				},
				{
					"hip1": 46509,
					"hip2": 46390
				},
				{
					"hip1": 46390,
					"hip2": 48356
				},
				{
					"hip1": 48356,
					"hip2": 49841
				},
				{
					"hip1": 49841,
					"hip2": 51069
				},
				{
					"hip1": 51069,
					"hip2": 52943
				},
				{
					"hip1": 52943,
					"hip2": 56343
				},
				{
					"hip1": 56343,
					"hip2": 57936
				},
				{
					"hip1": 57936,
					"hip2": 64166
				},
				{
					"hip1": 64166,
					"hip2": 64962
				}
			]
		},
		{
			"abbr": "Hyi",
			"lines": [
				{
					"hip1": 2021,
					"hip2": 17678
				},
				{
					"hip1": 17678,
					"hip2": 12394
				},
				{
					"hip1": 12394,
					"hip2": 11001
				},
				{
					"hip1": 11001,
					"hip2": 9236
				}
			]
		},
		{
			"abbr": "Ind",
			"lines": [
				{
					"hip1": 105319,
					"hip2": 101772
				},
				{
					"hip1": 101772,
					"hip2": 103227
				},
				{
					"hip1": 103227,
					"hip2": 105319
				}
			]
		},
		{
			"abbr": "Lac",
			"lines": [
				{
					"hip1": 109937,
					"hip2": 111104
				},
				{
					"hip1": 111104,
					"hip2": 111022
				},
				{
					"hip1": 111022,
					"hip2": 110609
				},
				{
					"hip1": 110609,
					"hip2": 110538
				},
				{
					"hip1": 110538,
					"hip2": 111169
				},
				{
					"hip1": 111169,
					"hip2": 111022
				}
			]
		},
		{
			"abbr": "Leo",
			"lines": [
				{
					"hip1": 57632,
					"hip2": 54879
				},
				{
					"hip1": 54879,
					"hip2": 49669
				},
				{
					"hip1": 49669,
					"hip2": 49583
				},
				{
					"hip1": 49583,
					"hip2": 50583
				},
				{
					"hip1": 50583,
					"hip2": 54872
				},
				{
					"hip1": 54872,
					"hip2": 57632
				},
				{
					"hip1": 50583,
					"hip2": 50335
				},
				{
					"hip1": 50335,
					"hip2": 48455
				},
				{
					"hip1": 48455,
					"hip2": 47908
				},
				{
					"hip1": 54872,
					"hip2": 54879
				}
			]
		},
		{
			"abbr": "Lep",
			"lines": [
				{
					"hip1": 28910,
					"hip2": 28103
				},
				{
					"hip1": 28103,
					"hip2": 27288
				},
				{
					"hip1": 27288,
					"hip2": 25985
				},
				{
					"hip1": 25985,
					"hip2": 24305
				},
				{
					"hip1": 25985,
					"hip2": 27654
				},
				{
					"hip1": 27654,
					"hip2": 27072
				},
				{
					"hip1": 27072,
					"hip2": 25606
				},
				{
					"hip1": 25606,
					"hip2": 23685
				},
				{
					"hip1": 25985,
					"hip2": 25606
				},
				{
					"hip1": 24305,
					"hip2": 24845
				},
				{
					"hip1": 24305,
					"hip2": 24327
				},
				{
					"hip1": 23685,
					"hip2": 24305
				},
				{
					"hip1": 24327,
					"hip2": 24244
				},
				{
					"hip1": 24845,
					"hip2": 24873
				}
			]
		},
		{
			"abbr": "Lib",
			"lines": [
				{
					"hip1": 77853,
					"hip2": 76333
				},
				{
					"hip1": 76333,
					"hip2": 74785
				},
				{
					"hip1": 74785,
					"hip2": 72622
				},
				{
					"hip1": 72622,
					"hip2": 73714
				},
				{
					"hip1": 73714,
					"hip2": 76333
				}
			]
		},
		{
			"abbr": "LMi",
			"lines": [
				{
					"hip1": 53229,
					"hip2": 51233
				},
				{
					"hip1": 51233,
					"hip2": 49593
				},
				{
					"hip1": 49593,
					"hip2": 46952
				},
				{
					"hip1": 49593,
					"hip2": 53229
				}
			]
		},
		{
			"abbr": "Lup",
			"lines": [
				{
					"hip1": 77634,
					"hip2": 78970
				},
				{
					"hip1": 78970,
					"hip2": 78384
				},
				{
					"hip1": 78384,
					"hip2": 77634
				},
				{
					"hip1": 78384,
					"hip2": 76297
				},
				{
					"hip1": 76297,
					"hip2": 75141
				},
				{
					"hip1": 75141,
					"hip2": 75177
				},
				{
					"hip1": 75141,
					"hip2": 73273
				},
				{
					"hip1": 76297,
					"hip2": 76552
				},
				{
					"hip1": 76552,
					"hip2": 74395
				},
				{
					"hip1": 74395,
					"hip2": 71860
				},
				{
					"hip1": 74395,
					"hip2": 71536
				},
				{
					"hip1": 71860,
					"hip2": 70576
				},
				{
					"hip1": 71860,
					"hip2": 73273
				}
			]
		},
		{
			"abbr": "Lyn",
			"lines": [
				{
					"hip1": 45860,
					"hip2": 45688
				},
				{
					"hip1": 45688,
					"hip2": 44700
				},
				{
					"hip1": 44700,
					"hip2": 44248
				},
				{
					"hip1": 44248,
					"hip2": 41075
				},
				{
					"hip1": 41075,
					"hip2": 36145
				},
				{
					"hip1": 36145,
					"hip2": 33449
				},
				{
					"hip1": 33449,
					"hip2": 30060
				}
			]
		},
		{
			"abbr": "Lyr",
			"lines": [
				{
					"hip1": 91262,
					"hip2": 91971
				},
				{
					"hip1": 91971,
					"hip2": 92420
				},
				{
					"hip1": 92420,
					"hip2": 93194
				},
				{
					"hip1": 93194,
					"hip2": 92791
				},
				{
					"hip1": 92791,
					"hip2": 91971
				}
			]
		},
		{
			"abbr": "Men",
			"lines": [
				{
					"hip1": 25918,
					"hip2": 21949
				}
			]
		},
		{
			"abbr": "Mic",
			"lines": [
				{
					"hip1": 105140,
					"hip2": 103738
				},
				{
					"hip1": 103738,
					"hip2": 102831
				}
			]
		},
		{
			"abbr": "Mon",
			"lines": [
				{
					"hip1": 29651,
					"hip2": 30867
				},
				{
					"hip1": 30867,
					"hip2": 34769
				},
				{
					"hip1": 34769,
					"hip2": 30419
				},
				{
					"hip1": 30419,
					"hip2": 29151
				},
				{
					"hip1": 34769,
					"hip2": 39863
				},
				{
					"hip1": 39863,
					"hip2": 37447
				}
			]
		},
		{
			"abbr": "Mus",
			"lines": [
				{
					"hip1": 62322,
					"hip2": 57363
				},
				{
					"hip1": 57363,
					"hip2": 61199
				},
				{
					"hip1": 61199,
					"hip2": 61585
				},
				{
					"hip1": 61585,
					"hip2": 62322
				}
			]
		},
		{
			"abbr": "Nor",
			"lines": [
				{
					"hip1": 79509,
					"hip2": 80000
				},
				{
					"hip1": 80000,
					"hip2": 80582
				},
				{
					"hip1": 80582,
					"hip2": 78639
				},
				{
					"hip1": 78639,
					"hip2": 80000
				},
				{
					"hip1": 78639,
					"hip2": 79509
				}
			]
		},
		{
			"abbr": "Oct",
			"lines": [
				{
					"hip1": 107089,
					"hip2": 112405
				},
				{
					"hip1": 112405,
					"hip2": 70638
				},
				{
					"hip1": 70638,
					"hip2": 107089
				}
			]
		},
		{
			"abbr": "Oph",
			"lines": [
				{
					"hip1": 86032,
					"hip2": 86742
				},
				{
					"hip1": 84012,
					"hip2": 86742
				},
				{
					"hip1": 86032,
					"hip2": 83000
				},
				{
					"hip1": 83000,
					"hip2": 79882
				},
				{
					"hip1": 79882,
					"hip2": 81377
				},
				{
					"hip1": 81377,
					"hip2": 84012
				},
				{
					"hip1": 84012,
					"hip2": 85755
				}
			]
		},
		{
			"abbr": "Ori",
			"lines": [
				{
					"hip1": 26727,
					"hip2": 26311
				},
				{
					"hip1": 26311,
					"hip2": 25930
				},
				{
					"hip1": 29434,
					"hip2": 29426
				},
				{
					"hip1": 29434,
					"hip2": 28716
				},
				{
					"hip1": 28716,
					"hip2": 27913
				},
				{
					"hip1": 29426,
					"hip2": 29038
				},
				{
					"hip1": 29038,
					"hip2": 27913
				},
				{
					"hip1": 29426,
					"hip2": 28614
				},
				{
					"hip1": 28614,
					"hip2": 27989
				},
				{
					"hip1": 27989,
					"hip2": 26727
				},
				{
					"hip1": 26727,
					"hip2": 27366
				},
				{
					"hip1": 27366,
					"hip2": 24436
				},
				{
					"hip1": 24436,
					"hip2": 25930
				},
				{
					"hip1": 25930,
					"hip2": 25336
				},
				{
					"hip1": 25336,
					"hip2": 26207
				},
				{
					"hip1": 26207,
					"hip2": 27989
				},
				{
					"hip1": 25336,
					"hip2": 22449
				},
				{
					"hip1": 22449,
					"hip2": 22549
				},
				{
					"hip1": 22549,
					"hip2": 22730
				},
				{
					"hip1": 22730,
					"hip2": 23123
				},
				{
					"hip1": 22449,
					"hip2": 22509
				},
				{
					"hip1": 22509,
					"hip2": 22845
				},
				{
					"hip1": 29038,
					"hip2": 28614
				}
			]
		},
		{
			"abbr": "Pav",
			"lines": [
				{
					"hip1": 100751,
					"hip2": 105858
				},
				{
					"hip1": 105858,
					"hip2": 102395
				},
				{
					"hip1": 102395,
					"hip2": 99240
				},
				{
					"hip1": 99240,
					"hip2": 100751
				},
				{
					"hip1": 99240,
					"hip2": 98495
				},
				{
					"hip1": 98495,
					"hip2": 91792
				},
				{
					"hip1": 91792,
					"hip2": 93015
				},
				{
					"hip1": 93015,
					"hip2": 99240
				},
				{
					"hip1": 93015,
					"hip2": 92609
				},
				{
					"hip1": 92609,
					"hip2": 90098
				},
				{
					"hip1": 90098,
					"hip2": 88866
				},
				{
					"hip1": 88866,
					"hip2": 92609
				},
				{
					"hip1": 88866,
					"hip2": 86929
				}
			]
		},
		{
			"abbr": "Peg",
			"lines": [
				{
					"hip1": 1067,
					"hip2": 113963
				},
				{
					"hip1": 113881,
					"hip2": 112158
				},
				{
					"hip1": 112158,
					"hip2": 109352
				},
				{
					"hip1": 113881,
					"hip2": 112748
				},
				{
					"hip1": 112748,
					"hip2": 112440
				},
				{
					"hip1": 112440,
					"hip2": 109176
				},
				{
					"hip1": 109176,
					"hip2": 107354
				},
				{
					"hip1": 113963,
					"hip2": 112447
				},
				{
					"hip1": 112447,
					"hip2": 112029
				},
				{
					"hip1": 112029,
					"hip2": 109427
				},
				{
					"hip1": 109427,
					"hip2": 107315
				},
				{
					"hip1": 677,
					"hip2": 113881
				},
				{
					"hip1": 677,
					"hip2": 1067
				},
				{
					"hip1": 113881,
					"hip2": 113963
				}
			]
		},
		{
			"abbr": "Per",
			"lines": [
				{
					"hip1": 17448,
					"hip2": 18246
				},
				{
					"hip1": 18246,
					"hip2": 18614
				},
				{
					"hip1": 18614,
					"hip2": 18532
				},
				{
					"hip1": 18532,
					"hip2": 17358
				},
				{
					"hip1": 17358,
					"hip2": 15863
				},
				{
					"hip1": 15863,
					"hip2": 14328
				},
				{
					"hip1": 14328,
					"hip2": 13268
				},
				{
					"hip1": 15863,
					"hip2": 14576
				},
				{
					"hip1": 14576,
					"hip2": 14354
				},
				{
					"hip1": 14354,
					"hip2": 13254
				}
			]
		},
		{
			"abbr": "Phe",
			"lines": [
				{
					"hip1": 5348,
					"hip2": 5165
				},
				{
					"hip1": 5165,
					"hip2": 2072
				},
				{
					"hip1": 2072,
					"hip2": 5348
				},
				{
					"hip1": 5165,
					"hip2": 7083
				},
				{
					"hip1": 7083,
					"hip2": 8837
				},
				{
					"hip1": 8837,
					"hip2": 5165
				},
				{
					"hip1": 5165,
					"hip2": 6867
				},
				{
					"hip1": 6867,
					"hip2": 2072
				},
				{
					"hip1": 2072,
					"hip2": 2081
				},
				{
					"hip1": 2081,
					"hip2": 765
				},
				{
					"hip1": 765,
					"hip2": 2072
				}
			]
		},
		{
			"abbr": "Pic",
			"lines": [
				{
					"hip1": 32607,
					"hip2": 27530
				},
				{
					"hip1": 27530,
					"hip2": 27321
				}
			]
		},
		{
			"abbr": "PsA",
			"lines": [
				{
					"hip1": 113368,
					"hip2": 111954
				},
				{
					"hip1": 111954,
					"hip2": 108661
				},
				{
					"hip1": 108661,
					"hip2": 107608
				},
				{
					"hip1": 107608,
					"hip2": 109422
				},
				{
					"hip1": 109422,
					"hip2": 111188
				},
				{
					"hip1": 111188,
					"hip2": 113246
				}
			]
		},
		{
			"abbr": "Psc",
			"lines": [
				{
					"hip1": 4889,
					"hip2": 5742
				},
				{
					"hip1": 4889,
					"hip2": 6193
				},
				{
					"hip1": 6193,
					"hip2": 5742
				},
				{
					"hip1": 5742,
					"hip2": 7097
				},
				{
					"hip1": 7097,
					"hip2": 8198
				},
				{
					"hip1": 8198,
					"hip2": 9487
				},
				{
					"hip1": 9487,
					"hip2": 8833
				},
				{
					"hip1": 8833,
					"hip2": 7884
				},
				{
					"hip1": 7884,
					"hip2": 7007
				},
				{
					"hip1": 7007,
					"hip2": 4906
				},
				{
					"hip1": 4906,
					"hip2": 3760
				},
				{
					"hip1": 3760,
					"hip2": 1645
				},
				{
					"hip1": 1645,
					"hip2": 118268
				},
				{
					"hip1": 118268,
					"hip2": 116771
				},
				{
					"hip1": 116771,
					"hip2": 116928
				},
				{
					"hip1": 116928,
					"hip2": 115738
				},
				{
					"hip1": 115738,
					"hip2": 114971
				},
				{
					"hip1": 114971,
					"hip2": 115830
				},
				{
					"hip1": 115830,
					"hip2": 116771
				}
			]
		},
		{
			"abbr": "Pup",
			"lines": [
				{
					"hip1": 39757,
					"hip2": 38146
				},
				{
					"hip1": 38146,
					"hip2": 35264
				},
				{
					"hip1": 35264,
					"hip2": 31685
				},
				{
					"hip1": 31685,
					"hip2": 32768
				},
				{
					"hip1": 32768,
					"hip2": 36377
				},
				{
					"hip1": 36377,
					"hip2": 39429
				},
				{
					"hip1": 39429,
					"hip2": 39757
				}
			]
		},
		{
			"abbr": "Pyx",
			"lines": [
				{
					"hip1": 42515,
					"hip2": 42828
				},
				{
					"hip1": 42828,
					"hip2": 43409
				}
			]
		},
		{
			"abbr": "Ret",
			"lines": [
				{
					"hip1": 19780,
					"hip2": 19921
				},
				{
					"hip1": 19921,
					"hip2": 18597
				},
				{
					"hip1": 18597,
					"hip2": 17440
				},
				{
					"hip1": 17440,
					"hip2": 19780
				}
			]
		},
		{
			"abbr": "Scl",
			"lines": [
				{
					"hip1": 116231,
					"hip2": 4577
				},
				{
					"hip1": 4577,
					"hip2": 115102
				},
				{
					"hip1": 115102,
					"hip2": 116231
				}
			]
		},
		{
			"abbr": "Sco",
			"lines": [
				{
					"hip1": 85927,
					"hip2": 86670
				},
				{
					"hip1": 86670,
					"hip2": 87073
				},
				{
					"hip1": 87073,
					"hip2": 86228
				},
				{
					"hip1": 86228,
					"hip2": 84143
				},
				{
					"hip1": 84143,
					"hip2": 82671
				},
				{
					"hip1": 82671,
					"hip2": 82514
				},
				{
					"hip1": 82514,
					"hip2": 82396
				},
				{
					"hip1": 82396,
					"hip2": 81266
				},
				{
					"hip1": 81266,
					"hip2": 80763
				},
				{
					"hip1": 80763,
					"hip2": 78401
				},
				{
					"hip1": 80763,
					"hip2": 78265
				},
				{
					"hip1": 80763,
					"hip2": 78820
				}
			]
		},
		{
			"abbr": "Sct",
			"lines": [
				{
					"hip1": 92175,
					"hip2": 92202
				},
				{
					"hip1": 92202,
					"hip2": 92814
				},
				{
					"hip1": 92814,
					"hip2": 90595
				},
				{
					"hip1": 90595,
					"hip2": 91117
				},
				{
					"hip1": 91117,
					"hip2": 92175
				}
			]
		},
		{
			"abbr": "Ser",
			"lines": [
				{
					"hip1": 77516,
					"hip2": 77622
				},
				{
					"hip1": 77622,
					"hip2": 77070
				},
				{
					"hip1": 77070,
					"hip2": 76276
				},
				{
					"hip1": 76276,
					"hip2": 77233
				},
				{
					"hip1": 77233,
					"hip2": 78072
				},
				{
					"hip1": 78072,
					"hip2": 77450
				},
				{
					"hip1": 77450,
					"hip2": 77233
				},
				{
					"hip1": 92946,
					"hip2": 89962
				},
				{
					"hip1": 89962,
					"hip2": 86565
				},
				{
					"hip1": 86565,
					"hip2": 86263
				},
				{
					"hip1": 86263,
					"hip2": 84880
				}
			]
		},
		{
			"abbr": "Sex",
			"lines": [
				{
					"hip1": 51437,
					"hip2": 49641
				}
			]
		},
		{
			"abbr": "Sge",
			"lines": [
				{
					"hip1": 96837,
					"hip2": 97365
				},
				{
					"hip1": 97365,
					"hip2": 96757
				},
				{
					"hip1": 97365,
					"hip2": 98337
				},
				{
					"hip1": 98337,
					"hip2": 98920
				}
			]
		},
		{
			"abbr": "Sgr",
			"lines": [
				{
					"hip1": 89931,
					"hip2": 90496
				},
				{
					"hip1": 89642,
					"hip2": 90185
				},
				{
					"hip1": 90185,
					"hip2": 88635
				},
				{
					"hip1": 88635,
					"hip2": 87072
				},
				{
					"hip1": 88635,
					"hip2": 89931
				},
				{
					"hip1": 89931,
					"hip2": 90185
				},
				{
					"hip1": 90185,
					"hip2": 93506
				},
				{
					"hip1": 93506,
					"hip2": 92041
				},
				{
					"hip1": 92041,
					"hip2": 89931
				},
				{
					"hip1": 92041,
					"hip2": 90496
				},
				{
					"hip1": 90496,
					"hip2": 89341
				},
				{
					"hip1": 93506,
					"hip2": 93864
				},
				{
					"hip1": 93864,
					"hip2": 92855
				},
				{
					"hip1": 92855,
					"hip2": 92041
				},
				{
					"hip1": 92855,
					"hip2": 93085
				},
				{
					"hip1": 93085,
					"hip2": 93683
				},
				{
					"hip1": 93683,
					"hip2": 94820
				},
				{
					"hip1": 94820,
					"hip2": 95168
				},
				{
					"hip1": 93864,
					"hip2": 96406
				},
				{
					"hip1": 96406,
					"hip2": 98688
				},
				{
					"hip1": 98688,
					"hip2": 98412
				},
				{
					"hip1": 98412,
					"hip2": 98032
				},
				{
					"hip1": 98032,
					"hip2": 95347
				},
				{
					"hip1": 98032,
					"hip2": 95294
				}
			]
		},
		{
			"abbr": "Tau",
			"lines": [
				{
					"hip1": 25428,
					"hip2": 21881
				},
				{
					"hip1": 21881,
					"hip2": 20889
				},
				{
					"hip1": 21421,
					"hip2": 26451
				},
				{
					"hip1": 20205,
					"hip2": 20455
				},
				{
					"hip1": 20205,
					"hip2": 18724
				},
				{
					"hip1": 18724,
					"hip2": 15900
				},
				{
					"hip1": 21421,
					"hip2": 20889
				},
				{
					"hip1": 21421,
					"hip2": 20894
				},
				{
					"hip1": 20894,
					"hip2": 20205
				},
				{
					"hip1": 20889,
					"hip2": 20648
				},
				{
					"hip1": 20648,
					"hip2": 20455
				},
				{
					"hip1": 20455,
					"hip2": 17847
				}
			]
		},
		{
			"abbr": "Tel",
			"lines": [
				{
					"hip1": 90568,
					"hip2": 90422
				}
			]
		},
		{
			"abbr": "TrA",
			"lines": [
				{
					"hip1": 82273,
					"hip2": 74946
				},
				{
					"hip1": 74946,
					"hip2": 77952
				},
				{
					"hip1": 77952,
					"hip2": 82273
				}
			]
		},
		{
			"abbr": "Tri",
			"lines": [
				{
					"hip1": 10670,
					"hip2": 10064
				},
				{
					"hip1": 10064,
					"hip2": 8796
				},
				{
					"hip1": 8796,
					"hip2": 10670
				}
			]
		},
		{
			"abbr": "Tuc",
			"lines": [
				{
					"hip1": 110130,
					"hip2": 114996
				},
				{
					"hip1": 114996,
					"hip2": 1599
				},
				{
					"hip1": 114996,
					"hip2": 2484
				}
			]
		},
		{
			"abbr": "UMa",
			"lines": [
				{
					"hip1": 67301,
					"hip2": 65378
				},
				{
					"hip1": 65378,
					"hip2": 62956
				},
				{
					"hip1": 62956,
					"hip2": 59774
				},
				{
					"hip1": 59774,
					"hip2": 54061
				},
				{
					"hip1": 54061,
					"hip2": 53910
				},
				{
					"hip1": 53910,
					"hip2": 58001
				},
				{
					"hip1": 58001,
					"hip2": 59774
				},
				{
					"hip1": 58001,
					"hip2": 57399
				},
				{
					"hip1": 57399,
					"hip2": 54539
				},
				{
					"hip1": 54539,
					"hip2": 50372
				},
				{
					"hip1": 54539,
					"hip2": 50801
				},
				{
					"hip1": 53910,
					"hip2": 48402
				},
				{
					"hip1": 48402,
					"hip2": 46853
				},
				{
					"hip1": 46853,
					"hip2": 44471
				},
				{
					"hip1": 46853,
					"hip2": 44127
				},
				{
					"hip1": 48402,
					"hip2": 48319
				},
				{
					"hip1": 48319,
					"hip2": 41704
				},
				{
					"hip1": 41704,
					"hip2": 46733
				},
				{
					"hip1": 46733,
					"hip2": 54061
				}
			]
		},
		{
			"abbr": "UMi",
			"lines": [
				{
					"hip1": 11767,
					"hip2": 85822
				},
				{
					"hip1": 85822,
					"hip2": 82080
				},
				{
					"hip1": 82080,
					"hip2": 77055
				},
				{
					"hip1": 77055,
					"hip2": 79822
				},
				{
					"hip1": 79822,
					"hip2": 75097
				},
				{
					"hip1": 75097,
					"hip2": 72607
				},
				{
					"hip1": 72607,
					"hip2": 77055
				}
			]
		},
		{
			"abbr": "Vel",
			"lines": [
				{
					"hip1": 39953,
					"hip2": 42536
				},
				{
					"hip1": 42536,
					"hip2": 42913
				},
				{
					"hip1": 42913,
					"hip2": 45941
				},
				{
					"hip1": 45941,
					"hip2": 48774
				},
				{
					"hip1": 48774,
					"hip2": 52727
				},
				{
					"hip1": 52727,
					"hip2": 51986
				},
				{
					"hip1": 51986,
					"hip2": 50191
				},
				{
					"hip1": 50191,
					"hip2": 46651
				},
				{
					"hip1": 46651,
					"hip2": 44816
				},
				{
					"hip1": 44816,
					"hip2": 39953
				}
			]
		},
		{
			"abbr": "Vir",
			"lines": [
				{
					"hip1": 57380,
					"hip2": 60129
				},
				{
					"hip1": 60129,
					"hip2": 61941
				},
				{
					"hip1": 61941,
					"hip2": 65474
				},
				{
					"hip1": 65474,
					"hip2": 69427
				},
				{
					"hip1": 69427,
					"hip2": 69701
				},
				{
					"hip1": 69701,
					"hip2": 71957
				},
				{
					"hip1": 65474,
					"hip2": 66249
				},
				{
					"hip1": 66249,
					"hip2": 68520
				},
				{
					"hip1": 68520,
					"hip2": 72220
				},
				{
					"hip1": 66249,
					"hip2": 63090
				},
				{
					"hip1": 63090,
					"hip2": 63608
				},
				{
					"hip1": 63090,
					"hip2": 61941
				}
			]
		},
		{
			"abbr": "Vol",
			"lines": [
				{
					"hip1": 37504,
					"hip2": 34481
				},
				{
					"hip1": 34481,
					"hip2": 39794
				},
				{
					"hip1": 39794,
					"hip2": 37504
				},
				{
					"hip1": 39794,
					"hip2": 35228
				},
				{
					"hip1": 39794,
					"hip2": 41312
				},
				{
					"hip1": 41312,
					"hip2": 44382
				},
				{
					"hip1": 44382,
					"hip2": 39794
				}
			]
		},
		{
			"abbr": "Vul",
			"lines": [
				{
					"hip1": 95771,
					"hip2": 98543
				}
			]
		}
	],
	"totalLines": 676
}
